{
  "creator": "Yosys 0.61+112 (git sha1 ac427a79b-dirty, x86_64-w64-mingw32-g++ 13.2.1 -O3)",
  "modules": {
    "top": {
      "attributes": {
        "top": "00000000000000000000000000000001",
        "src": "top.v:1.1-19.10"
      },
      "ports": {
        "a_s": {
          "direction": "input",
          "signed": 1,
          "bits": [ 2, 3, 4, 5 ]
        },
        "b_s": {
          "direction": "input",
          "signed": 1,
          "bits": [ 6, 7, 8, 9 ]
        },
        "a_u": {
          "direction": "input",
          "bits": [ 10, 11, 12, 13 ]
        },
        "b_u": {
          "direction": "input",
          "bits": [ 14, 15, 16, 17 ]
        },
        "y_s_lt": {
          "direction": "output",
          "bits": [ 18 ]
        },
        "y_s_ge": {
          "direction": "output",
          "bits": [ 19 ]
        },
        "y_u_lt": {
          "direction": "output",
          "bits": [ 20 ]
        },
        "y_u_ge": {
          "direction": "output",
          "bits": [ 21 ]
        }
      },
      "cells": {
        "$ge$top.v:14$2": {
          "hide_name": 1,
          "type": "$ge",
          "parameters": {
            "A_SIGNED": "00000000000000000000000000000001",
            "A_WIDTH": "00000000000000000000000000000100",
            "B_SIGNED": "00000000000000000000000000000001",
            "B_WIDTH": "00000000000000000000000000000100",
            "Y_WIDTH": "00000000000000000000000000000001"
          },
          "attributes": {
            "src": "top.v:14.20-14.30"
          },
          "port_directions": {
            "A": "input",
            "B": "input",
            "Y": "output"
          },
          "connections": {
            "A": [ 2, 3, 4, 5 ],
            "B": [ 6, 7, 8, 9 ],
            "Y": [ 19 ]
          }
        },
        "$ge$top.v:17$4": {
          "hide_name": 1,
          "type": "$ge",
          "parameters": {
            "A_SIGNED": "00000000000000000000000000000000",
            "A_WIDTH": "00000000000000000000000000000100",
            "B_SIGNED": "00000000000000000000000000000000",
            "B_WIDTH": "00000000000000000000000000000100",
            "Y_WIDTH": "00000000000000000000000000000001"
          },
          "attributes": {
            "src": "top.v:17.20-17.30"
          },
          "port_directions": {
            "A": "input",
            "B": "input",
            "Y": "output"
          },
          "connections": {
            "A": [ 10, 11, 12, 13 ],
            "B": [ 14, 15, 16, 17 ],
            "Y": [ 21 ]
          }
        },
        "$lt$top.v:13$1": {
          "hide_name": 1,
          "type": "$lt",
          "parameters": {
            "A_SIGNED": "00000000000000000000000000000001",
            "A_WIDTH": "00000000000000000000000000000100",
            "B_SIGNED": "00000000000000000000000000000001",
            "B_WIDTH": "00000000000000000000000000000100",
            "Y_WIDTH": "00000000000000000000000000000001"
          },
          "attributes": {
            "src": "top.v:13.20-13.30"
          },
          "port_directions": {
            "A": "input",
            "B": "input",
            "Y": "output"
          },
          "connections": {
            "A": [ 2, 3, 4, 5 ],
            "B": [ 6, 7, 8, 9 ],
            "Y": [ 18 ]
          }
        },
        "$lt$top.v:16$3": {
          "hide_name": 1,
          "type": "$lt",
          "parameters": {
            "A_SIGNED": "00000000000000000000000000000000",
            "A_WIDTH": "00000000000000000000000000000100",
            "B_SIGNED": "00000000000000000000000000000000",
            "B_WIDTH": "00000000000000000000000000000100",
            "Y_WIDTH": "00000000000000000000000000000001"
          },
          "attributes": {
            "src": "top.v:16.20-16.30"
          },
          "port_directions": {
            "A": "input",
            "B": "input",
            "Y": "output"
          },
          "connections": {
            "A": [ 10, 11, 12, 13 ],
            "B": [ 14, 15, 16, 17 ],
            "Y": [ 20 ]
          }
        }
      },
      "netnames": {
        "a_s": {
          "hide_name": 0,
          "bits": [ 2, 3, 4, 5 ],
          "signed": 1,
          "attributes": {
            "src": "top.v:2.23-2.26"
          }
        },
        "a_u": {
          "hide_name": 0,
          "bits": [ 10, 11, 12, 13 ],
          "attributes": {
            "src": "top.v:4.23-4.26"
          }
        },
        "b_s": {
          "hide_name": 0,
          "bits": [ 6, 7, 8, 9 ],
          "signed": 1,
          "attributes": {
            "src": "top.v:3.23-3.26"
          }
        },
        "b_u": {
          "hide_name": 0,
          "bits": [ 14, 15, 16, 17 ],
          "attributes": {
            "src": "top.v:5.23-5.26"
          }
        },
        "y_s_ge": {
          "hide_name": 0,
          "bits": [ 19 ],
          "attributes": {
            "src": "top.v:8.10-8.16"
          }
        },
        "y_s_lt": {
          "hide_name": 0,
          "bits": [ 18 ],
          "attributes": {
            "src": "top.v:7.10-7.16"
          }
        },
        "y_u_ge": {
          "hide_name": 0,
          "bits": [ 21 ],
          "attributes": {
            "src": "top.v:10.10-10.16"
          }
        },
        "y_u_lt": {
          "hide_name": 0,
          "bits": [ 20 ],
          "attributes": {
            "src": "top.v:9.10-9.16"
          }
        }
      }
    }
  }
}
